setup.py
yubikey.py
yubikey.egg-info/PKG-INFO
yubikey.egg-info/SOURCES.txt
yubikey.egg-info/dependency_links.txt
yubikey.egg-info/top_level.txt