Metadata-Version: 1.0
Name: yubikey
Version: 0.2
Summary: Validate a Yubikey against Yubico's web-service
Home-page: UNKNOWN
Author: kaleissin
Author-email: kaleissin at gmail com
License: MIT
Keywords: yubikey auth web-services
Platform: UNKNOWN
